README.md
crunchy/__init__.py
crunchy/__main__.py
crunchy/cli/__init__.py
crunchy/cli/auto_cmd.py
crunchy/cli/base.py
crunchy/cli/checksum_cmd.py
crunchy/cli/compare_cmd.py
crunchy/cli/compress_cmd.py
crunchy/cli/decompress_cmd.py
crunchy/cli/utils.py
crunchy/command.py
crunchy/compress.py
crunchy/decompress.py
crunchy/files.py
crunchy/integrity.py
crunchy/metadata.py
crunchy/utils.py
crunchy/version.py
tests/__init__.py
tests/cli/conftest.py
tests/cli/test_auto_cmd.py
tests/cli/test_compare.py
tests/cli/test_compress_cmd.py
tests/cli/test_decompress_cmd.py
tests/command/conftest.py
tests/command/test_command.py
tests/conftest.py
tests/fixtures/bam/test.bam
tests/fixtures/bam/test.bam.bai
tests/fixtures/bam/test.cram
tests/fixtures/bam/test.cram.crai
tests/fixtures/bam/test.sam
tests/fixtures/dummy.txt
tests/fixtures/fastq/TEST_R1_001.fq.gz
tests/fixtures/fastq/TEST_R2_001.fq.gz
tests/fixtures/reference.fasta
tests/fixtures/reference.fasta.fai
tests/fixtures/spring/TEST.spring
tests/fixtures/zipped_file.txt
tests/fixtures/zipped_file.txt.gz
tests/test_compress.py
tests/test_decompress.py
tests/test_files.py
tests/test_integrity.py
tests/test_main.py
tests/test_metadata.py
tests/test_utils.py
crunchy-1.0.13.dist-info/LICENSE
crunchy-1.0.13.dist-info/METADATA
crunchy-1.0.13.dist-info/WHEEL
crunchy-1.0.13.dist-info/entry_points.txt
crunchy-1.0.13.dist-info/RECORD
