Metadata-Version: 2.1
Name: crunchy
Version: 1.0.13
Summary: Compress fastq files with spring and check the integrity
License: MIT
Author: Your Name
Author-email: you@example.com
Requires-Python: >=3.12,<4.0
Classifier: License :: OSI Approved :: MIT License
Classifier: Programming Language :: Python :: 3
Classifier: Programming Language :: Python :: 3.12
Classifier: Programming Language :: Python :: 3.13
Requires-Dist: click
Requires-Dist: coloredlogs
Requires-Dist: importlib-metadata
Requires-Dist: setuptools
Requires-Dist: zipp
